{
  "file": "Ambient/PE/Applications.lean",
  "title": "Applications",
  "status": "scaffold",
  "summary": "Aggregate entry point for the PE renormalized-curvature-integral theorem and Pfaffian application.",
  "mathematicalContent": [
    {
      "heading": "Mathematical role",
      "body": "Aggregate entry point for the PE renormalized-curvature-integral theorem and Pfaffian application.",
      "formula": null
    },
    {
      "heading": "How to read the translation",
      "body": "The correspondence below follows Ambient/PE/Applications.lean declaration by declaration. A definition is translated by its defining expression, a theorem by its quantified proposition, and a structure, class, or inductive type by the mathematical data encoded in its fields or constructors. The original Lean signature remains visible beside every translation.",
      "formula": null
    }
  ],
  "correspondence": [],
  "prerequisites": [
    "Ambient/PE/Applications/CaseKhaitanLinTyrrellYuan.lean",
    "Ambient/PE/Applications/PfaffianApplication.lean"
  ],
  "usedBy": [
    "Ambient/PE.lean"
  ],
  "references": [
    {
      "referenceId": "CaseKhaitanLinTyrrellYuan-2024",
      "locator": "Proposition 3.7, Proposition 3.10, Lemma 4.1, and Theorems 1.1/1.4 as applicable",
      "note": "Primary source for the renormalized-curvature-integral mechanism represented by these modules."
    },
    {
      "referenceId": "FG-AmbientMetric",
      "locator": "Chapter 4",
      "note": "Background for the ambient/Poincaré correspondence."
    }
  ],
  "limitations": "This file establishes syntax, aggregate imports, or an abstract bridge. It must not be read as a derivation of the corresponding geometric theorem from concrete tensor and analytic data."
}
